pybastion/__init__.py
pybastion/analyzers/__init__.py
pybastion/analyzers/queries/__init__.py
pybastion/analyzers/queries/security.py
pybastion/analyzers/rules/__init__.py
pybastion/analyzers/rules/cis_benchmarks/__init__.py
pybastion/analyzers/rules/cis_benchmarks/cisco.py
pybastion/analyzers/sql/__init__.py
pybastion/analyzers/sql/analyzer.py
pybastion/api_clients/__init__.py
pybastion/api_clients/cve_details.py
pybastion/api_clients/endoflife.py
pybastion/core/database.py
pybastion/core/exceptions.py
pybastion/core/scanner.py
pybastion/models/__init__.py
pybastion/models/analysis/__init__.py
pybastion/models/api_clients/__init__.py
pybastion/models/base/__init__.py
pybastion/models/base/enums.py
pybastion/models/base/mixins.py
pybastion/models/base/types.py
pybastion/models/base/validators.py
pybastion/models/cisco_asa/__init__.py
pybastion/models/cisco_ios/__init__.py
pybastion/models/fortigate/__init__.py
pybastion/models/normalized/__init__.py
pybastion/models/normalized/device.py
pybastion/models/paloalto/__init__.py
pybastion/parsers/__init__.py
pybastion/parsers/factory.py
pybastion/parsers/base/__init__.py
pybastion/parsers/base/parser.py
pybastion/parsers/cisco_asa/__init__.py
pybastion/parsers/cisco_asa/parser.py
pybastion/parsers/cisco_asa/commands/__init__.py
pybastion/parsers/cisco_ios/__init__.py
pybastion/parsers/cisco_ios/parser.py
pybastion/parsers/cisco_ios/commands/__init__.py
pybastion/parsers/fortigate/__init__.py
pybastion/parsers/fortigate/parser.py
pybastion/parsers/fortigate/commands/__init__.py
pybastion/parsers/paloalto/__init__.py
pybastion/parsers/paloalto/parser.py
pybastion/parsers/paloalto/commands/__init__.py
pybastion/reports/__init__.py
pybastion/reports/generator.py
pybastion/reports/queries/__init__.py
pybastion/reports/templates/__init__.py
pybastion/reports/templates/html_report.py
pybastion/utils/__init__.py
pybastion/utils/logging.py
pybastion/utils/network.py
pybastion-0.0.1.dev0.dist-info/licenses/LICENSE
pybastion-0.0.1.dev0.dist-info/METADATA
pybastion-0.0.1.dev0.dist-info/WHEEL
pybastion-0.0.1.dev0.dist-info/entry_points.txt
pybastion-0.0.1.dev0.dist-info/top_level.txt
pybastion-0.0.1.dev0.dist-info/RECORD
