Metadata-Version: 2.4
Name: PyBastion
Version: 0.0.1.dev0
Summary: Network device configuration security analysis tool (Development Version - Not Production Ready)
Author-email: Randy <randy@example.com>
License: MIT
Project-URL: Homepage, https://github.com/flyguy62n/pybastion
Project-URL: Repository, https://github.com/flyguy62n/pybastion.git
Project-URL: Issues, https://github.com/flyguy62n/pybastion/issues
Keywords: network,security,configuration,analysis,cisco,fortinet,paloalto
Classifier: Development Status :: 2 - Pre-Alpha
Classifier: Intended Audience :: System Administrators
Classifier: License :: OSI Approved :: MIT License
Classifier: Programming Language :: Python :: 3
Classifier: Programming Language :: Python :: 3.12
Classifier: Topic :: System :: Networking
Classifier: Topic :: Security
Requires-Python: >=3.12
License-File: LICENSE
Requires-Dist: sqlmodel>=0.0.16
Requires-Dist: duckdb>=0.10.0
Requires-Dist: click>=8.1.0
Requires-Dist: pydantic>=2.5.0
Requires-Dist: httpx>=0.27.0
Requires-Dist: rich>=13.7.0
Requires-Dist: openpyxl>=3.1.0
Requires-Dist: jinja2>=3.1.0
Requires-Dist: pyyaml>=6.0.0
Requires-Dist: python-dateutil>=2.8.0
Provides-Extra: dev
Requires-Dist: pytest>=8.3.5; extra == "dev"
Requires-Dist: pytest-cov>=5.0.0; extra == "dev"
Requires-Dist: pytest-asyncio>=0.21.0; extra == "dev"
Requires-Dist: ruff>=0.1.0; extra == "dev"
Requires-Dist: mypy>=1.7.0; extra == "dev"
Requires-Dist: pre-commit>=3.6.0; extra == "dev"
Dynamic: license-file
